Workbook

Sheet orcamento_empresa
A1: CONTROLE - DISPÊNDIOS POR RECURSO
A2: PLANO DE TRABALHO CONSOLIDADO EMPRESA
A3: DISPÊNDIOS | B3: VALOR (R$) | C3: %
A4: I - programas de computador, máquinas, equipamentos, aparelhos e instrumentos, seus acessórios, sobressalentes e ferramentas, e serviços de instalação dessas máquinas e equipamentos utilizados na execução do projeto; | B4: 0 | C4: =IF($B$20=0,0,B4/$B$20) -> 0
A5: II - aquisição, implantação, ampliação ou modernização de infraestrutura física e de laboratórios de pesquisa, desenvolvimento e inovação e de ICTs; | B5: 0 | C5: =IF($B$20=0,0,B5/$B$20) -> 0
A6: III - RH direto | B6: 0 | C6: =IF($B$20=0,0,B6/$B$20) -> 0
A7: III - RH indireto | B7: 0 | C7: =IF($B$20=0,0,B7/$B$20) -> 0
A8: IV - Serviços Técnicos de Terceiros | B8: 8937 | C8: =IF($B$20=0,0,B8/$B$20) -> 0.081245455
A9: V - Mat. Consumo | B9: 0 | C9: =IF($B$20=0,0,B9/$B$20) -> 0
A10: Total Dispêndios (I a V) | B10: =SUM(B4:B9) -> 8937 | C10: =IF($B$20=0,0,B10/$B$20) -> 0.081245455
A11: VI - Outros dispêndios correlatos às atividades de pesquisa, desenvolvimento e inovação. | B11: =SUM(B12:B16) -> 28800 | C11: =IF($B$20=0,0,B11/$B$20) -> 0.26181818
A12: Publicações e Treinamentos | B12: 0 | C12: =IF($B$20=0,0,B12/$B$20) -> 0
A13: Despesas de suporte operacional | B13: 22400 | C13: =IF($B$20=0,0,B13/$B$20) -> 0.20363636
A14: Tarifas Bancárias | B14: 0 | C14: =IF($B$20=0,0,B14/$B$20) -> 0
A15: ISS | B15: 5500 | C15: =IF($B$20=0,0,B15/$B$20) -> 0.05
A16: Outros(Aluguel, Internet, Telefonia, Impostos Etc) | B16: 900 | C16: =IF($B$20=0,0,B16/$B$20) -> 0.0081818182
A17: Total Dispêndios (I a VI) | B17: =B11+B10 -> 37737 | C17: =IF($B$20=0,0,B17/$B$20) -> 0.34306364
A18: DOA (Despesas operacionais e Administrativas) | B18: 60883 | C18: =IF($B$20=0,0,B18/$B$20) -> 0.55348182
A19: Constituição de Reserva | B19: 11380 | C19: =IF($B$20=0,0,B19/$B$20) -> 0.10345455
A20: TOTAL | B20: =B17+B18+B19 -> 110000 | C20: =IF($B$20=0,0,B20/$B$20) -> 1

Sheet orcamento_embrabii
A1: CONTROLE - DISPÊNDIOS POR RECURSO
A2: PLANO DE TRABALHO CONSOLIDADO EMPRESA
A3: DISPÊNDIOS | B3: VALOR (R$) | C3: %
A4: I - programas de computador, máquinas, equipamentos, aparelhos e instrumentos, seus acessórios, sobressalentes e ferramentas, e serviços de instalação dessas máquinas e equipamentos utilizados na execução do projeto; | B4: 0 | C4: =IF($B$20=0,0,B4/$B$20) -> 0
A5: II - aquisição, implantação, ampliação ou modernização de infraestrutura física e de laboratórios de pesquisa, desenvolvimento e inovação e de ICTs; | B5: 0 | C5: =IF($B$20=0,0,B5/$B$20) -> 0
A6: III - RH direto | B6: 309000 | C6: =IF($B$20=0,0,B6/$B$20) -> 1
A7: III - RH indireto | B7: 0 | C7: =IF($B$20=0,0,B7/$B$20) -> 0
A8: IV - Serviços Técnicos de Terceiros | B8: 0 | C8: =IF($B$20=0,0,B8/$B$20) -> 0
A9: V - Mat. Consumo | B9: 0 | C9: =IF($B$20=0,0,B9/$B$20) -> 0
A10: Total Dispêndios (I a V) | B10: =SUM(B4:B9) -> 309000 | C10: =IF($B$20=0,0,B10/$B$20) -> 1
A11: VI - Outros dispêndios correlatos às atividades de pesquisa, desenvolvimento e inovação. | B11: =SUM(B12:B16) -> 0 | C11: =IF($B$20=0,0,B11/$B$20) -> 0
A12: Publicações e Treinamentos | B12: 0 | C12: =IF($B$20=0,0,B12/$B$20) -> 0
A13: Despesas de suporte operacional | B13: 0 | C13: =IF($B$20=0,0,B13/$B$20) -> 0
A14: Tarifas Bancárias | B14: 0 | C14: =IF($B$20=0,0,B14/$B$20) -> 0
A15: ISS | B15: 0 | C15: =IF($B$20=0,0,B15/$B$20) -> 0
A16: Outros(Aluguel, Internet, Telefonia, Impostos Etc) | B16: 0 | C16: =IF($B$20=0,0,B16/$B$20) -> 0
A17: Total Dispêndios (I a VI) | B17: =B11+B10 -> 309000 | C17: =IF($B$20=0,0,B17/$B$20) -> 1
A18: DOA (Despesas operacionais e Administrativas) | B18: 0 | C18: =IF($B$20=0,0,B18/$B$20) -> 0
A19: Constituição de Reserva | B19: 0 | C19: =IF($B$20=0,0,B19/$B$20) -> 0
A20: TOTAL | B20: =B17+B18+B19 -> 309000 | C20: =IF($B$20=0,0,B20/$B$20) -> 1

Sheet orcamento_sebrae
A1: CONTROLE - DISPÊNDIOS POR RECURSO
A2: PLANO DE TRABALHO CONSOLIDADO EMPRESA
A3: DISPÊNDIOS | B3: VALOR (R$) | C3: %
A4: I - programas de computador, máquinas, equipamentos, aparelhos e instrumentos, seus acessórios, sobressalentes e ferramentas, e serviços de instalação dessas máquinas e equipamentos utilizados na execução do projeto; | B4: 0 | C4: =IF($B$20=0,0,B4/$B$20) -> 0
A5: II - aquisição, implantação, ampliação ou modernização de infraestrutura física e de laboratórios de pesquisa, desenvolvimento e inovação e de ICTs; | B5: 0 | C5: =IF($B$20=0,0,B5/$B$20) -> 0
A6: III - RH direto | B6: 149000 | C6: =IF($B$20=0,0,B6/$B$20) -> 0.99333333
A7: III - RH indireto | B7: 0 | C7: =IF($B$20=0,0,B7/$B$20) -> 0
A8: IV - Serviços Técnicos de Terceiros | B8: 0 | C8: =IF($B$20=0,0,B8/$B$20) -> 0
A9: V - Mat. Consumo | B9: 0 | C9: =IF($B$20=0,0,B9/$B$20) -> 0
A10: Total Dispêndios (I a V) | B10: =SUM(B4:B9) -> 149000 | C10: =IF($B$20=0,0,B10/$B$20) -> 0.99333333
A11: VI - Outros dispêndios correlatos às atividades de pesquisa, desenvolvimento e inovação. | B11: =SUM(B12:B16) -> 1000 | C11: =IF($B$20=0,0,B11/$B$20) -> 0.0066666667
A12: Publicações e Treinamentos | B12: 0 | C12: =IF($B$20=0,0,B12/$B$20) -> 0
A13: Despesas de suporte operacional | B13: 0 | C13: =IF($B$20=0,0,B13/$B$20) -> 0
A14: Tarifas Bancárias | B14: 1000 | C14: =IF($B$20=0,0,B14/$B$20) -> 0.0066666667
A15: ISS | B15: 0 | C15: =IF($B$20=0,0,B15/$B$20) -> 0
A16: Outros(Aluguel, Internet, Telefonia, Impostos Etc) | B16: 0 | C16: =IF($B$20=0,0,B16/$B$20) -> 0
A17: Total Dispêndios (I a VI) | B17: =B11+B10 -> 150000 | C17: =IF($B$20=0,0,B17/$B$20) -> 1
A18: DOA (Despesas operacionais e Administrativas) | B18: 0 | C18: =IF($B$20=0,0,B18/$B$20) -> 0
A19: Constituição de Reserva | B19: 0 | C19: =IF($B$20=0,0,B19/$B$20) -> 0
A20: TOTAL | B20: =B17+B18+B19 -> 150000 | C20: =IF($B$20=0,0,B20/$B$20) -> 1

Sheet orcamento_biocaroco
A1: CONTROLE - DISPÊNDIOS POR RECURSO
A2: PLANO DE TRABALHO CONSOLIDADO EMPRESA
A3: DISPÊNDIOS | B3: VALOR (R$) | C3: %
A4: I - programas de computador, máquinas, equipamentos, aparelhos e instrumentos, seus acessórios, sobressalentes e ferramentas, e serviços de instalação dessas máquinas e equipamentos utilizados na execução do projeto; | B4: =orcamento_empresa!B4+orcamento_embrabii!B4+orcamento_sebrae!B4 -> 0 | C4: =IF($B$20=0,0,B4/$B$20) -> 0
A5: II - aquisição, implantação, ampliação ou modernização de infraestrutura física e de laboratórios de pesquisa, desenvolvimento e inovação e de ICTs; | B5: =orcamento_empresa!B5+orcamento_embrabii!B5+orcamento_sebrae!B5 -> 0 | C5: =IF($B$20=0,0,B5/$B$20) -> 0
A6: III - RH direto | B6: =orcamento_empresa!B6+orcamento_embrabii!B6+orcamento_sebrae!B6 -> 458000 | C6: =IF($B$20=0,0,B6/$B$20) -> 0.80492091
A7: III - RH indireto | B7: =orcamento_empresa!B7+orcamento_embrabii!B7+orcamento_sebrae!B7 -> 0 | C7: =IF($B$20=0,0,B7/$B$20) -> 0
A8: IV - Serviços Técnicos de Terceiros | B8: =orcamento_empresa!B8+orcamento_embrabii!B8+orcamento_sebrae!B8 -> 8937 | C8: =IF($B$20=0,0,B8/$B$20) -> 0.015706503
A9: V - Mat. Consumo | B9: =orcamento_empresa!B9+orcamento_embrabii!B9+orcamento_sebrae!B9 -> 0 | C9: =IF($B$20=0,0,B9/$B$20) -> 0
A10: Total Dispêndios (I a V) | B10: =orcamento_empresa!B10+orcamento_embrabii!B10+orcamento_sebrae!B10 -> 466937 | C10: =IF($B$20=0,0,B10/$B$20) -> 0.82062742
A11: VI - Outros dispêndios correlatos às atividades de pesquisa, desenvolvimento e inovação. | B11: =orcamento_empresa!B11+orcamento_embrabii!B11+orcamento_sebrae!B11 -> 29800 | C11: =IF($B$20=0,0,B11/$B$20) -> 0.052372583
A12: Publicações e Treinamentos | B12: =orcamento_empresa!B12+orcamento_embrabii!B12+orcamento_sebrae!B12 -> 0 | C12: =IF($B$20=0,0,B12/$B$20) -> 0
A13: Despesas de suporte operacional | B13: =orcamento_empresa!B13+orcamento_embrabii!B13+orcamento_sebrae!B13 -> 22400 | C13: =IF($B$20=0,0,B13/$B$20) -> 0.039367311
A14: Tarifas Bancárias | B14: =orcamento_empresa!B14+orcamento_embrabii!B14+orcamento_sebrae!B14 -> 1000 | C14: =IF($B$20=0,0,B14/$B$20) -> 0.0017574692
A15: ISS | B15: =orcamento_empresa!B15+orcamento_embrabii!B15+orcamento_sebrae!B15 -> 5500 | C15: =IF($B$20=0,0,B15/$B$20) -> 0.0096660808
... A19: Constituição de Reserva | B19: =orcamento_empresa!B19+orcamento_embrabii!B19+orcamento_sebrae!B19 -> 11380 | C19: =IF($B$20=0,0,B19/$B$20) -> 0.02
A20: TOTAL | B20: =B17+B18+B19 -> 569000 | C20: =IF($B$20=0,0,B20/$B$20) -> 1
