Workbook

Sheet det_execucao_orcamentaria
A1: Rubrica | B1: Previsto | C1: %Previsto | D1: Executado | E1: Disponível | F1: %execucao_item | G1: %execucao_geral
A2: I - Programa de Computador e Equipamento | B2: =[1]orcamento_biocaroco!$B$4 -> 0 | C2: 1 | D2: ='[2]Cronograma Desembolso'!$E$4 -> 0 | E2: =det_execucao_orcamentaria[[#This Row],[Previsto]]-det_execucao_orcamentaria[[#This Row],[Executado]] -> 0 | F2: =IF(det_execucao_orcamentaria[[#This Row],[Previsto]]=0,0,det_execucao_orcamentaria[[#This Row],[Executado]]/det_execucao_orcamentaria[[#This Row],[Previsto]]) -> 0 | G2: =det_execucao_orcamentaria[[#This Row],[Executado]]/det_execucao_orcamentaria[[#Totals],[Previsto]] -> 0
A3: II - Modernização de Infraestrutura | B3: =[1]orcamento_biocaroco!$B$5 -> 0 | C3: 1 | D3: ='[2]Cronograma Desembolso'!$E$5 -> 0 | E3: =det_execucao_orcamentaria[[#This Row],[Previsto]]-det_execucao_orcamentaria[[#This Row],[Executado]] -> 0 | F3: =IF(det_execucao_orcamentaria[[#This Row],[Previsto]]=0,0,det_execucao_orcamentaria[[#This Row],[Executado]]/det_execucao_orcamentaria[[#This Row],[Previsto]]) -> 0 | G3: =det_execucao_orcamentaria[[#This Row],[Executado]]/det_execucao_orcamentaria[[#Totals],[Previsto]] -> 0
A4: III - RH Direto | B4: =[1]orcamento_biocaroco!$B$6 -> 458000 | C4: 1 | D4: ='[2]Cronograma Desembolso'!$E$6 -> 134250 | E4: =det_execucao_orcamentaria[[#This Row],[Previsto]]-det_execucao_orcamentaria[[#This Row],[Executado]] -> 323750 | F4: =IF(det_execucao_orcamentaria[[#This Row],[Previsto]]=0,"",det_execucao_orcamentaria[[#This Row],[Executado]]/det_execucao_orcamentaria[[#This Row],[Previsto]]) -> 0.29312227 | G4: =det_execucao_orcamentaria[[#This Row],[Executado]]/det_execucao_orcamentaria[[#Totals],[Previsto]] -> 0.23594025
A5: III - RH Indireto | B5: ='[2]Cronograma Desembolso'!$D$19 -> 0 | C5: 1 | D5: ='[2]Cronograma Desembolso'!$E$19 -> 0 | E5: =det_execucao_orcamentaria[[#This Row],[Previsto]]-det_execucao_orcamentaria[[#This Row],[Executado]] -> 0 | F5: =IF(det_execucao_orcamentaria[[#This Row],[Previsto]]=0,"",det_execucao_orcamentaria[[#This Row],[Executado]]/det_execucao_orcamentaria[[#This Row],[Previsto]]) | G5: =det_execucao_orcamentaria[[#This Row],[Executado]]/det_execucao_orcamentaria[[#Totals],[Previsto]] -> 0
A6: IV - Serviços Técnicos de Terceiros | B6: =[1]orcamento_biocaroco!$B$8 -> 8937 | C6: 1 | D6: ='[2]Cronograma Desembolso'!$E$20 -> 0 | E6: =det_execucao_orcamentaria[[#This Row],[Previsto]]-det_execucao_orcamentaria[[#This Row],[Executado]] -> 8937 | F6: =IF(det_execucao_orcamentaria[[#This Row],[Previsto]]=0,"",det_execucao_orcamentaria[[#This Row],[Executado]]/det_execucao_orcamentaria[[#This Row],[Previsto]]) -> 0 | G6: =det_execucao_orcamentaria[[#This Row],[Executado]]/det_execucao_orcamentaria[[#Totals],[Previsto]] -> 0
A7: V - Materiais de Consumo (Protótipo) | B7: =[1]orcamento_biocaroco!$B$9 -> 0 | C7: 1 | D7: ='[2]Cronograma Desembolso'!$E$23 -> 0 | E7: =det_execucao_orcamentaria[[#This Row],[Previsto]]-det_execucao_orcamentaria[[#This Row],[Executado]] -> 0 | F7: =IF(det_execucao_orcamentaria[[#This Row],[Previsto]]=0,0,det_execucao_orcamentaria[[#This Row],[Executado]]/det_execucao_orcamentaria[[#This Row],[Previsto]]) -> 0 | G7: =det_execucao_orcamentaria[[#This Row],[Executado]]/det_execucao_orcamentaria[[#Totals],[Previsto]] -> 0
A8: VI - Outros Dispêndios Correlatos | D8: ='[2]Cronograma Desembolso'!$E$5 -> 0 | E8: =det_execucao_orcamentaria[[#This Row],[Previsto]]-det_execucao_orcamentaria[[#This Row],[Executado]] -> 0 | F8: =IF(det_execucao_orcamentaria[[#This Row],[Previsto]]=0,0,det_execucao_orcamentaria[[#This Row],[Executado]]/det_execucao_orcamentaria[[#This Row],[Previsto]]) -> 0
A9: DOA (FAEPI) | B9: =[1]orcamento_biocaroco!$B$18 -> 60883 | C9: 1 | D9: ='[2]Cronograma Desembolso'!$E$30 -> 0 | E9: =det_execucao_orcamentaria[[#This Row],[Previsto]]-det_execucao_orcamentaria[[#This Row],[Executado]] -> 60883 | F9: =IF(det_execucao_orcamentaria[[#This Row],[Previsto]]=0,0,det_execucao_orcamentaria[[#This Row],[Executado]]/det_execucao_orcamentaria[[#This Row],[Previsto]]) -> 0 | G9: =det_execucao_orcamentaria[[#This Row],[Executado]]/det_execucao_orcamentaria[[#Totals],[Previsto]] -> 0
A10: Fundo de Reserva (IFAM) | B10: =[1]orcamento_biocaroco!$B$19 -> 11380 | C10: 1 | D10: ='[2]Cronograma Desembolso'!$E$31 -> 0 | E10: =det_execucao_orcamentaria[[#This Row],[Previsto]]-det_execucao_orcamentaria[[#This Row],[Executado]] -> 11380 | F10: =IF(det_execucao_orcamentaria[[#This Row],[Previsto]]=0,0,det_execucao_orcamentaria[[#This Row],[Executado]]/det_execucao_orcamentaria[[#This Row],[Previsto]]) -> 0 | G10: =det_execucao_orcamentaria[[#This Row],[Executado]]/det_execucao_orcamentaria[[#Totals],[Previsto]] -> 0
A11: ISS | B11: 5500 | C11: 1 | D11: ='[2]Cronograma Desembolso'!$E$32 -> 0 | E11: =det_execucao_orcamentaria[[#This Row],[Previsto]]-det_execucao_orcamentaria[[#This Row],[Executado]] -> 5500 | F11: =IF(det_execucao_orcamentaria[[#This Row],[Previsto]]=0,0,det_execucao_orcamentaria[[#This Row],[Executado]]/det_execucao_orcamentaria[[#This Row],[Previsto]]) -> 0 | G11: =det_execucao_orcamentaria[[#This Row],[Executado]]/det_execucao_orcamentaria[[#Totals],[Previsto]] -> 0
A12: Outros Correlatos (Internet) | B12: =[1]orcamento_biocaroco!$B$16 -> 900 | C12: 1 | D12: ='[2]Cronograma Desembolso'!$E$30 -> 0 | E12: =det_execucao_orcamentaria[[#This Row],[Previsto]]-det_execucao_orcamentaria[[#This Row],[Executado]] -> 900 | F12: =IF(det_execucao_orcamentaria[[#This Row],[Previsto]]=0,0,det_execucao_orcamentaria[[#This Row],[Executado]]/det_execucao_orcamentaria[[#This Row],[Previsto]]) -> 0 | G12: =det_execucao_orcamentaria[[#This Row],[Executado]]/det_execucao_orcamentaria[[#Totals],[Previsto]] -> 0
A13: Despesas de Suporte Operacional | B13: ='[2]Cronograma Desembolso'!$D$28 -> 22400 | C13: 1 | D13: ='[2]Cronograma Desembolso'!$E$28 -> 8400 | E13: =det_execucao_orcamentaria[[#This Row],[Previsto]]-det_execucao_orcamentaria[[#This Row],[Executado]] -> 14000 | F13: =IF(det_execucao_orcamentaria[[#This Row],[Previsto]]=0,0,det_execucao_orcamentaria[[#This Row],[Executado]]/det_execucao_orcamentaria[[#This Row],[Previsto]]) -> 0.375 | G13: =det_execucao_orcamentaria[[#This Row],[Executado]]/det_execucao_orcamentaria[[#Totals],[Previsto]] -> 0.014762742
A14: Tarifas Bancárias | B14: =[1]orcamento_biocaroco!$B$14 -> 1000 | C14: 1 | D14: ='[2]Cronograma Desembolso'!$E$27 -> 0 | E14: =det_execucao_orcamentaria[[#This Row],[Previsto]]-det_execucao_orcamentaria[[#This Row],[Executado]] -> 1000 | F14: =IF(det_execucao_orcamentaria[[#This Row],[Previsto]]=0,0,det_execucao_orcamentaria[[#This Row],[Executado]]/det_execucao_orcamentaria[[#This Row],[Previsto]]) -> 0 | G14: =det_execucao_orcamentaria[[#This Row],[Executado]]/det_execucao_orcamentaria[[#Totals],[Previsto]] -> 0
A15: Total | B15: =SUBTOTAL(109,det_execucao_orcamentaria[Previsto]) -> 569000 | D15: =SUBTOTAL(109,det_execucao_orcamentaria[Executado]) -> 142650 | E15: =SUBTOTAL(109,det_execucao_orcamentaria[Disponível]) -> 426350 | G15: =SUBTOTAL(109,det_execucao_orcamentaria[%execucao_geral]) -> 0.25070299

Sheet Slide 2 - Saude do Projeto
B2: POLO DE INOVACAO MANAUS - CONVENIO N 002/2026 (BIO CAROCO)
B3: Dashboard de Saude do Projeto - Posicao Fechada em Setembro/2026 (Vinculado Dinamicamente)
B5: SALDO DISPONIVEL | D5: RECEITAS RECEBIDAS | F5: TOTAL EXECUTADO | H5: RENDIMENTO FINANC. | J5: SPRINTS ACOMP.
B6: ='Slide 3 - Desembolso e Contas'!J8 -> 137823.81 | D6: ='Slide 3 - Desembolso e Contas'!E14 -> 280500 | F6: ='Slide 2 - Saude do Projeto'!F17 -> 147173.83 | H6: ='Slide 3 - Desembolso e Contas'!J14 -> 4722.14 | J6: Sprints 14 e 15
B7: Fechamento em 30/09/2026 | D7: Aportes acumulados em conta | F7: Execucao financeira total | H7: Rendimento liquido aplicacao | J7: Ciclo operacional ativo
B9: EXECUCAO ORCAMENTARIA POR RUBRICA - ORCAMENTO * EXECUTADO * DISPONIVEL
B10: Rubrica Orcamentaria | D10: Orcamento (R$) | F10: Executado (R$) | H10: Disponivel (R$) | J10: Exec. %
B11: Recursos Humanos - Bolsas P&D | D11: =det_execucao_orcamentaria!B4 -> 458000 | F11: =det_execucao_orcamentaria!D4 -> 134250 | H11: =D11-F11 -> 323750 | J11: =IF(D11=0,0,F11/D11) -> 0.29312227
B12: Recursos Humanos Indiretos | D12: =det_execucao_orcamentaria!B5 -> 0 | F12: =det_execucao_orcamentaria!D5 -> 0 | H12: =D12-F12 -> 0 | J12: =IF(D12=0,0,F12/D12) -> 0
B13: Servicos de Terceiros PJ (Rateio Internet) | D13: =det_execucao_orcamentaria!B6+det_execucao_orcamentaria!B12 -> 9837 | F13: =-([3]extrato_bancario!$J$15 + [3]extrato_bancario!$J$16) -> 257.15 | H13: =D13-F13 -> 9579.85 | J13: =IF(D13=0,0,F13/D13) -> 0.0261411
B14: Tributos / ISS FAEPI | D14: =det_execucao_orcamentaria!B11 -> 5500 | F14: =-([3]extrato_bancario!$J$3 + [3]extrato_bancario!$J$4) -> 4125 | H14: =D14-F14 -> 1375 | J14: =IF(D14=0,0,F14/D14) -> 0.75
B15: Tarifas Bancarias (Conta SEBRAE) | D15: =det_execucao_orcamentaria!B14 -> 1000 | F15: =-SUM([3]extrato_bancario!$J$56:$J$63) -> 141.68 | H15: =D15-F15 -> 858.32 | J15: =IF(D15=0,0,F15/D15) -> 0.14168
B16: Despesa de Suporte Operacional (DOA) | D16: =det_execucao_orcamentaria!B9+det_execucao_orcamentaria!B10+det_execucao_orcamentaria!B13 -> 94663 | F16: =det_execucao_orcamentaria!D13 -> 8400 | H16: =D16-F16 -> 86263 | J16: =IF(D16=0,0,F16/D16) -> 0.088735831
B17: TOTAL DO PROJETO | D17: =SUM(D11:D16) -> 569000 | F17: =SUM(F11:F16) -> 147173.83 | H17: =SUM(H11:H16) -> 421826.17 | J17: =F17/D17 -> 0.25865348
B18: ="* Posicao em 30/09/2026. Aportado: R$ " & TEXT('Slide 3 - Desembolso e Contas'!E14, "#.##0,00") & ". Rendimentos liq.: R$ " & TEXT('Slide 3 - Desembolso e Contas'!J14, "#.##0,00") & ". Saldo em caixa: R$ " & TEXT('Slide 3 - Desembolso e Contas'!J8, "#.##0,00") & ". Tarifas Empresa/EMBRAPII pagas c/ rendimentos." -> * Posicao em 30/09/2026. Aportado: R$ 280.500,00. Rendimentos liq.: R$ 4.722,14. Saldo em caixa: R$ 137.823,81. Tarifas Empresa/EMBRAPII pagas c/ rendimentos.

Sheet Slide 3 - Desembolso e Contas
B2: CONV. 002/2026 - DESEMBOLSO E EXECUCAO ORCAMENTARIA (SETEMBRO/2026)
B3: Contas Bancarias: 15334-6 (Empresa), 15335-4 (SEBRAE), 15338-9 (EMBRAPII) - Vinculado Dinamicamente
B5: PARCELAS RECEBIDAS (ENTRADAS DE RECEITA) | H5: RESUMO FINANCEIRO CONSOLIDADO
B6: Parcela | C6: No Doc. | D6: Data Pagto | E6: Valor (R$) | F6: Acumulado (R$) | H6: Creditos de setembro (Rend. Bruto) | J6: ='Slide 3 - Desembolso e Contas'!J12 -> 332.27
B7: 01/03 EMB | C7: Ordem Banc. | D7: =[3]extrato_bancario!$B$72 -> 46190 | E7: =[3]extrato_bancario!$J$72 -> 103000 | F7: =E7 -> 103000 | H7: Debitos de setembro (Pagamentos) | J7: 61440.33
B8: 01/04 Emp | C8: NFSe 106 | D8: =[3]extrato_bancario!$B$2 -> 46204 | E8: =[3]extrato_bancario!$J$2 -> 27500 | F8: =F7+E8 -> 130500 | H8: Saldo Financeiro em 30/09 | J8: =SUM([3]extrato_bancario!$J$2:$J$85) -> 137823.81
B9: Unica SEB | C9: Aporte Unico | D9: =[3]extrato_bancario!$B$29 -> 46211 | E9: =[3]extrato_bancario!$J$29 -> 150000 | F9: =F8+E9 -> 280500
B10: 02/04 Emp | C10: - | D10: Prev. Out/26 | E10: 27500 | F10: pendente | H10: RENDIMENTOS DE APLICACAO FINANCEIRA
B11: 02/03 EMB | C11: - | D11: Prev. Out/26 | E11: 103000 | F11: pendente | H11: Saldo inicial acumulado (Ago) | J11: 4414.24
B12: 03/04 Emp | C12: - | D12: Prev. Dez/26 | E12: 27500 | F12: pendente | H12: Setembro/2026 - bruto | J12: 332.27
B13: 03/03 EMB | C13: - | D13: Prev. Jan/27 | E13: 103000 | F13: pendente | H13: Setembro/2026 - IRRF retido | J13: 24.37
B14: TOTAL RECEBIDO | E14: =SUM(E7:E9) -> 280500 | H14: Acumulado Liquido (30/09) | J14: =J11+J12-J13 -> 4722.14
B15: ="Receitas recebidas: R$ " & TEXT(E14, "#.##0,00") & " (" & TEXT(E14/'Slide 2 - Saude do Projeto'!D17, "0,0%") & " do convenio). Aportes pendentes: R$ " & TEXT('Slide 2 - Saude do Projeto'!D17-E14, "#.##0,00") & "." -> Receitas recebidas: R$ 280.500,00 (49,3% do convenio). Aportes pendentes: R$ 288.500,00.

Sheet Slide 4 - Analise e Atencao
B2: CONV. 002/2026 - ANALISE DE EXECUCAO E PONTOS DE ATENCAO (SETEMBRO/2026)
B3: Percentuais de Execucao por Rubrica e Destaques Gerenciais - Vinculado Dinamicamente
B5: % DE EXECUCAO POR RUBRICA ORCAMENTARIA | G5: EXECUCAO ACUMULADA GERAL
B6: Rubrica Orcamentaria | E6: % Exec. | G6: ='Slide 2 - Saude do Projeto'!J17 -> 0.25865348
B7: Recursos Humanos Diretos (Bolsas) | E7: ='Slide 2 - Saude do Projeto'!J11 -> 0.29312227 | G7: ="R$ " & TEXT('Slide 2 - Saude do Projeto'!F17, "#.##0,00") & " executados de R$ " & TEXT('Slide 2 - Saude do Projeto'!D17, "#.##0,00") & " do orcamento total" -> R$ 147.173,83 executados de R$ 569.000,00 do orcamento total
B8: Recursos Humanos Indiretos | E8: ='Slide 2 - Saude do Projeto'!J12 -> 0
B9: Tributos / ISS FAEPI | E9: ='Slide 2 - Saude do Projeto'!J14 -> 0.75 | G9: SALDO FINANCEIRO DISPONIVEL
B10: Tarifas Bancarias (SEBRAE) | E10: ='Slide 2 - Saude do Projeto'!J15 -> 0.14168 | G10: ='Slide 2 - Saude do Projeto'!B6 -> 137823.81
B11: Servicos Terceiros PJ (Rateio) | E11: ='Slide 2 - Saude do Projeto'!J13 -> 0.0261411 | G11: Disponibilidade imediata em 30/09/2026 (3 contas)
B12: Despesa Suporte Operacional (DOA) | E12: ='Slide 2 - Saude do Projeto'!J16 -> 0.088735831
G13: PONTOS DE ATENCAO - SETEMBRO/2026
G14: - Integralizacao SEBRAE: Aporte 100% integralizado em conta unica (R$ 150.000,00), garantindo liquidez continua.
G15: - Regularidade de Bolsas: 100% das bolsas do 1o trimestre quitadas e conciliadas com a FAEPI (34 ordens bancarias).
G16: - Proximos Aportes: Empresa Parcela 02/04 (R$ 27,5k) e EMBRAPII Parcela 02/03 (R$ 103k) previstas p/ o 4o mes.
G17: - Despesas Operacionais: Auxiliar Administrativo alocado em DSO (R$ 8,4k executados / 11,6%). Tarifas SEBRAE com R$ 858,32 de saldo.
